eagerx/__init__.py
eagerx/backends/__init__.py
eagerx/backends/ros1.py
eagerx/backends/single_process.py
eagerx/core/__init__.py
eagerx/core/colab_render.py
eagerx/core/constants.py
eagerx/core/entities.py
eagerx/core/env.py
eagerx/core/executable_engine.py
eagerx/core/executable_node.py
eagerx/core/graph.py
eagerx/core/graph_engine.py
eagerx/core/info.py
eagerx/core/log.py
eagerx/core/nodes.py
eagerx/core/pubsub.py
eagerx/core/register.py
eagerx/core/rx_message_broker.py
eagerx/core/rx_operators.py
eagerx/core/rx_pipelines.py
eagerx/core/space.py
eagerx/core/specs.py
eagerx/core/supervisor.py
eagerx/core/view.py
eagerx/engines/__init__.py
eagerx/engines/openai_gym/__init__.py
eagerx/engines/openai_gym/engine.py
eagerx/engines/openai_gym/enginenodes.py
eagerx/engines/openai_gym/env.py
eagerx/engines/openai_gym/objects.py
eagerx/utils/__init__.py
eagerx/utils/network_utils.py
eagerx/utils/node_utils.py
eagerx/utils/utils.py
eagerx/utils/utils_sub.py
eagerx/wrappers/__init__.py
eagerx/wrappers/flatten.py
eagerx-0.1.40.dist-info/METADATA
eagerx-0.1.40.dist-info/WHEEL
eagerx-0.1.40.dist-info/RECORD
