Metadata-Version: 2.1
Name: eagerx
Version: 0.1.40
Summary: Engine Angostic Graph Environments for Robotics
Home-page: https://github.com/eager-dev/eagerx
License: Apache2.0
Author: Bas van der Heijden
Author-email: d.s.vanderheijden@tudelft.nl
Requires-Python: >=3.7,<4.0
Classifier: License :: Other/Proprietary License
Classifier: Programming Language :: Python :: 3
Classifier: Programming Language :: Python :: 3.7
Classifier: Programming Language :: Python :: 3.8
Classifier: Programming Language :: Python :: 3.9
Classifier: Programming Language :: Python :: 3.10
Classifier: Programming Language :: Python :: 3.11
Classifier: Programming Language :: Python :: 3.12
Requires-Dist: Pillow (>=8.0,<9.0)
Requires-Dist: PyVirtualDisplay (>=3.0,<4.0)
Requires-Dist: PyYAML (>=6.0,<7.0)
Requires-Dist: Rx (>=3.2.0,<4.0.0)
Requires-Dist: Sphinx (>=4,<6)
Requires-Dist: defusedxml (>=0.7.1,<0.8.0)
Requires-Dist: gymnasium[classic-control] (>=0.28.1,<0.29.0)
Requires-Dist: matplotlib (>=3.0,<4.0)
Requires-Dist: netifaces (>=0.11.0,<0.12.0)
Requires-Dist: networkx (>=2.5.1,<3.0.0)
Requires-Dist: opencv-python (>=4.3.0.36,<5.0.0.0)
Requires-Dist: psutil (>=5.9.0,<6.0.0)
Requires-Dist: pyglet (>=1.5.21,<2.0.0)
Requires-Dist: rospkg (>=1.3.0,<2.0.0)
Requires-Dist: scipy (>=1.0,<2.0)
Requires-Dist: sphinx-autodoc-typehints (>=1.0,<2.0)
Requires-Dist: sphinx-rtd-theme (>=1.0,<2.0)
Requires-Dist: tabulate (>=0.8.9,<0.9.0)
Requires-Dist: termcolor (>=1.1.0,<2.0.0)
Project-URL: Documentation, https://eagerx.readthedocs.io/en/master/
Project-URL: Repository, https://github.com/eager-dev/eagerx
